bytecomp/__init__.py
bytecomp-1.1.0.dist-info/METADATA
bytecomp-1.1.0.dist-info/WHEEL
bytecomp-1.1.0.dist-info/top_level.txt
bytecomp-1.1.0.dist-info/RECORD
