Metadata-Version: 2.1
Name: bytecomp
Version: 1.1.0
Summary: Utilities to work with bytecode.
Home-page: https://github.com/dekrypted/bytecomp
Author: DeKrypt
Author-email: gregcoolkidd@gmail.com
Project-URL: Bug Tracker, https://github.com/dekrypted/bytecomp/issues
Keywords: bytecode,python
Classifier: Intended Audience :: Developers
Classifier: Programming Language :: Python :: 3
Classifier: License :: OSI Approved :: MIT License
Classifier: Operating System :: OS Independent
Requires-Python: >=3.5
